prose/__init__.py
prose/__version__.py
prose/cli.py
trashy_poetry-1.0.3.dist-info/entry_points.txt
trashy_poetry-1.0.3.dist-info/LICENSE
trashy_poetry-1.0.3.dist-info/WHEEL
trashy_poetry-1.0.3.dist-info/METADATA
trashy_poetry-1.0.3.dist-info/RECORD
