Metadata-Version: 2.1
Name: trashy-poetry
Version: 1.0.3
Summary: Poetry for everyday use
Home-page: https://github.com/pizzapanther/prose
License: MIT
Author: Paul Bailey
Author-email: paul@neutron.studio
Requires-Python: >=3.6,<4.0
Classifier: License :: OSI Approved :: MIT License
Classifier: Programming Language :: Python :: 3
Classifier: Programming Language :: Python :: 3.6
Classifier: Programming Language :: Python :: 3.7
Classifier: Programming Language :: Python :: 3.8
Classifier: Programming Language :: Python :: 3.9
Requires-Dist: poethepoet (>=0.10.0,<0.11.0)
Requires-Dist: poetry (>=1.1.4,<2.0.0)
Requires-Dist: python-dotenv (>=0.15.0,<0.16.0)
Project-URL: Repository, https://github.com/pizzapanther/prose
